.pypirc
MANIFEST.in
README.rst
distribute-0.6.24.tar.gz
setup.py
Products/__init__.py
Products.ArchAddOn.egg-info/PKG-INFO
Products.ArchAddOn.egg-info/SOURCES.txt
Products.ArchAddOn.egg-info/dependency_links.txt
Products.ArchAddOn.egg-info/entry_points.txt
Products.ArchAddOn.egg-info/namespace_packages.txt
Products.ArchAddOn.egg-info/not-zip-safe
Products.ArchAddOn.egg-info/requires.txt
Products.ArchAddOn.egg-info/top_level.txt
Products/ArchAddOn/AUTHORS
Products/ArchAddOn/Example.py
Products/ArchAddOn/Fields.py
Products/ArchAddOn/LICENSE.txt
Products/ArchAddOn/Validators.py
Products/ArchAddOn/Widgets.py
Products/ArchAddOn/__init__.py
Products/ArchAddOn/config.py
Products/ArchAddOn/configure.zcml
Products/ArchAddOn/public.py
Products/ArchAddOn/Extensions/Install.py
Products/ArchAddOn/skins/archaddon/getDataGridRow.py
Products/ArchAddOn/skins/archaddon/archaddon_widgets/email.pt
Products/ArchAddOn/skins/archaddon/archaddon_widgets/instruction.pt
Products/ArchAddOn/skins/archaddon/archaddon_widgets/link.pt
Products/ArchAddOn/tests/__init__.py
Products/ArchAddOn/tests/base.py
Products/ArchAddOn/tests/test_fields.py
Products/ArchAddOn/tests/test_setup.py
docs/HISTORY.txt
docs/INSTALL.txt
docs/LICENSE.GPL
docs/LICENSE.txt