Metadata-Version: 1.0
Name: Products.ArchAddOn
Version: 1.7
Summary: Straightforward toolbox of field types, widgets, and validators for Archetypes.
Home-page: https://github.com/collective/Products.ArchAddOn/
Author: Alex Clark
Author-email: aclark@aclark.net
License: GPL
Keywords: archetypes plone widget
Platform: UNKNOWN
Classifier: Framework :: Plone
Classifier: Programming Language :: Python
Classifier: Topic :: Software Development :: Libraries :: Python Modules
